proxyrotation/__init__.py
proxyrotation/common.py
proxyrotation/modelling.py
proxyrotation/repository/__init__.py
proxyrotation/repository/async.py
proxyrotation/repository/sequential.py
proxyrotation/rotator.py
proxyrotation-0.3.0.dist-info/LICENSE
proxyrotation-0.3.0.dist-info/METADATA
proxyrotation-0.3.0.dist-info/WHEEL
proxyrotation-0.3.0.dist-info/RECORD
