Metadata-Version: 2.1
Name: proxyrotation
Version: 0.3.0
Summary: automatic free proxy rotation
License: MIT
Keywords: proxy-rotation,web-scraping,anonymity
Author: Federico Minutoli
Author-email: fede97.minutoli@gmail.com
Requires-Python: >=3.9,<3.10
Classifier: License :: OSI Approved :: MIT License
Classifier: Programming Language :: Python :: 3
Classifier: Programming Language :: Python :: 3.9
Provides-Extra: async
Requires-Dist: aiohttp (>=3.9,<3.10) ; extra == "async"
Requires-Dist: aiostream (>=0.5,<0.6) ; extra == "async"
Requires-Dist: beautifulsoup4 (>=4.12,<4.13)
Requires-Dist: more-itertools (>=10.2,<10.3)
Requires-Dist: requests (>=2.31,<2.32)
Requires-Dist: uvloop (>=0.19,<0.20) ; sys_platform != "win32"
